koma/__init__.py
koma/clustering.py
koma/modal.py
koma/oma.py
koma/plot.py
koma/signal.py
koma/spatial.py
pykoma-1.3.6.dist-info/LICENSE
pykoma-1.3.6.dist-info/METADATA
pykoma-1.3.6.dist-info/WHEEL
pykoma-1.3.6.dist-info/top_level.txt
pykoma-1.3.6.dist-info/RECORD
