Metadata-Version: 2.1
Name: pykoma
Version: 1.3.6
Summary: Knuts Operational Modal Analysis
Author-email: "Knut A. Kvaale" <knut.a.kvale@ntnu.no>
License: MIT License
Project-URL: repository, https://github.com/knutankv/koma
Project-URL: documentation, https://knutankv.github.io/koma/
Classifier: License :: OSI Approved :: MIT License
Classifier: Operating System :: OS Independent
Classifier: Programming Language :: Python :: 3
Classifier: Topic :: Scientific/Engineering
Requires-Python: >=3.6
License-File: LICENSE
Requires-Dist: plotly
Requires-Dist: pandas
Requires-Dist: numpy
Requires-Dist: pyvista[jupyter]>=0.38.1
Requires-Dist: scikit-learn
Requires-Dist: trame
Requires-Dist: ipywidgets
Requires-Dist: pyvistaqt
